pybluecurrent/__init__.py
pybluecurrent/_version.py
pybluecurrent/client.py
pybluecurrent/exceptions.py
pybluecurrent/py.typed
pybluecurrent/utilities.py
pybluecurrent-0.1.0.dist-info/licenses/LICENSE
pybluecurrent-0.1.0.dist-info/METADATA
pybluecurrent-0.1.0.dist-info/WHEEL
pybluecurrent-0.1.0.dist-info/top_level.txt
pybluecurrent-0.1.0.dist-info/RECORD
