Metadata-Version: 2.4
Name: pybluecurrent
Version: 0.1.0
Summary: Python client for BlueCurrent charge points.
Author-email: Rogier van der Geer <rogier@vander-geer.nl>
License: MIT
Project-URL: Repository, https://github.com/rogiervandergeer/pybluecurrent
Keywords: api,blue current,electric vehicle,ev
Classifier: Intended Audience :: Developers
Classifier: License :: OSI Approved :: MIT License
Classifier: Operating System :: OS Independent
Classifier: Programming Language :: Python :: 3
Classifier: Typing :: Typed
Requires-Python: >=3.10
License-File: LICENSE
Requires-Dist: asyncio-multisubscriber-queue>=0.4.1
Requires-Dist: httpx>=0.28
Requires-Dist: sjcl>=0.2.1
Requires-Dist: websockets>=14.0
Provides-Extra: dev
Requires-Dist: black==23.3.0; extra == "dev"
Requires-Dist: pre-commit>=3.3.3; extra == "dev"
Requires-Dist: pytest==8.4.2; extra == "dev"
Requires-Dist: pytest-asyncio==1.2.0; extra == "dev"
Dynamic: license-file
